chemspace_vis
