Metadata-Version: 2.1
Name: chemspace-vis
Version: 0.1.1
Summary: Chemspace visualizer
Home-page: https://github.com/gregorpatof/chemspace_vis_package
Author: Olivier Mailhot
License: UNKNOWN
Platform: UNKNOWN
Classifier: Programming Language :: Python :: 3
Classifier: License :: OSI Approved :: MIT License
Classifier: Operating System :: OS Independent
Requires-Python: >=3.6
